[{"pk": 1, "model": "omb.remoteprofile", "fields": {"username": "skabber", "created": "2008-09-23 21:27:08", "url": "http://identi.ca/skabber", "secret": "dfdfa5e2d56b1305fd40955d59f2abe8", "uri": "http://identi.ca/user/15818", "update_profile_url": "http://identi.ca/index.php?action=updateprofile", "token": "d4fca6978e56a0e2d4d3b3a7ca31e3f0", "post_notice_url": "http://identi.ca/index.php?action=postnotice"}}, {"pk": 2, "model": "omb.remoteprofile", "fields": {"username": "ombtest", "created": "2008-09-25 23:17:00", "url": "http://identi.ca/ombtest", "secret": "4899f55bf3800f047c1d5fe351e3926e", "uri": "http://identi.ca/user/25580", "update_profile_url": "http://identi.ca/index.php?action=updateprofile", "token": "5f757984d6b9a209234875bdd62e345c", "post_notice_url": "http://identi.ca/index.php?action=postnotice"}}]
